onstar/__init__.py
onstar/demo.py
onstar/onstar.py
onstar/opel_onstar.py
onstar-0.1.2.dist-info/LICENSE.txt
onstar-0.1.2.dist-info/METADATA
onstar-0.1.2.dist-info/WHEEL
onstar-0.1.2.dist-info/top_level.txt
onstar-0.1.2.dist-info/RECORD
