Metadata-Version: 2.1
Name: onstar
Version: 0.1.2
Summary: Utility to get data from OnStar service specially from myopel.
Home-page: https://github.com/nyxnyx/onstar
Author: Grzegorz Szostak
Author-email: szostak.grzegorz@gmail.com
License: MIT
Platform: UNKNOWN
Classifier: Development Status :: 3 - Alpha
Classifier: Intended Audience :: Information Technology
Classifier: License :: OSI Approved :: MIT License
Classifier: Programming Language :: Python :: 3
Requires-Dist: aiohttp
